physipandas/__init__.py
physipandas/_version.py
physipandas/dataframe.py
physipandas/extension.py
physipandas/series.py
test/__init__.py
test/test_extension_array.py
test/test_extension_dtype.py
physipandas-0.1.0.dist-info/LICENSE
physipandas-0.1.0.dist-info/METADATA
physipandas-0.1.0.dist-info/WHEEL
physipandas-0.1.0.dist-info/top_level.txt
physipandas-0.1.0.dist-info/RECORD
