Metadata-Version: 2.1
Name: physipandas
Version: 0.1.0
Summary: Pandas extension for the physipy package.
Home-page: https://github.com/mocquin/physipandas
Author: mocquin
Author-email: mocquin@me.com
License: MIT
Keywords: pandas physics physical unit units dimension quantity quantities
License-File: LICENSE
Requires-Dist: physipy
Requires-Dist: pandas
